README.rst
setup.py
fitters/__init__.py
fitters/bayesian.py
fitters/linear.py
fitters/utils.py
fitting_utilities.egg-info/PKG-INFO
fitting_utilities.egg-info/SOURCES.txt
fitting_utilities.egg-info/dependency_links.txt
fitting_utilities.egg-info/requires.txt
fitting_utilities.egg-info/top_level.txt