Metadata-Version: 1.1
Name: fitting-utilities
Version: 0.1.0
Summary: Various useful classes for fitting stuff.
Home-page: UNKNOWN
Author: Kevin Gullikson
Author-email: kevin.gullikson@gmail.com
License: MIT
Platform: UNKNOWN
Classifier: Development Status :: 3 - Alpha
Classifier: Intended Audience :: Science/Research
Classifier: License :: OSI Approved :: MIT License
Classifier: Programming Language :: Python
Classifier: Topic :: Scientific/Engineering :: Astronomy
